PrettyConfig/__init__.py
PrettyConfig/fork.py
PrettyConfig/hyperparameters.py
PrettyConfig-0.0.1.dist-info/LICENSE
PrettyConfig-0.0.1.dist-info/METADATA
PrettyConfig-0.0.1.dist-info/WHEEL
PrettyConfig-0.0.1.dist-info/top_level.txt
PrettyConfig-0.0.1.dist-info/RECORD
